fssg/__init__.py
fssg/cli.py
fssg/config.py
fssg/core.py
fssg/errors.py
fssg/renderer.py
fssg-1.1.0.dist-info/METADATA
fssg-1.1.0.dist-info/WHEEL
fssg-1.1.0.dist-info/entry_points.txt
fssg-1.1.0.dist-info/top_level.txt
fssg-1.1.0.dist-info/RECORD
